tinymce/__init__.py
tinymce/apps.py
tinymce/models.py
tinymce/settings.py
tinymce/templates/tinymce/spellchecker.js
tinymce/templates/tinymce/tinymce4.css
tinymce/templates/tinymce/tinymce_init.js
tinymce/urls.py
tinymce/views.py
tinymce/widgets.py
django_tinymce4_widget-7.1.1.dist-info/LICENSE.txt
django_tinymce4_widget-7.1.1.dist-info/METADATA
django_tinymce4_widget-7.1.1.dist-info/WHEEL
django_tinymce4_widget-7.1.1.dist-info/RECORD
