Metadata-Version: 2.1
Name: django-tinymce4-widget
Version: 7.1.1
Summary: A Django application that provides a TinyMCE 4 editor widget without any static files
Home-page: https://github.com/browniebroke/django-tinymce4-widget
License: MIT
Keywords: django,wysiwyg,widget,tinymce
Author: Bruno Alla
Author-email: oss@browniebroke.com
Requires-Python: >=3.8,<4.0
Classifier: Development Status :: 5 - Production/Stable
Classifier: Environment :: Web Environment
Classifier: Framework :: Django
Classifier: Framework :: Django :: 3.2
Classifier: Framework :: Django :: 4.0
Classifier: Framework :: Django :: 4.1
Classifier: Framework :: Django :: 4.2
Classifier: Framework :: Django :: 5.0
Classifier: Intended Audience :: Developers
Classifier: License :: OSI Approved :: MIT License
Classifier: Natural Language :: English
Classifier: Operating System :: OS Independent
Classifier: Programming Language :: Python :: 3
Classifier: Programming Language :: Python :: 3.8
Classifier: Programming Language :: Python :: 3.9
Classifier: Programming Language :: Python :: 3.10
Classifier: Programming Language :: Python :: 3.11
Classifier: Programming Language :: Python :: 3.12
Classifier: Topic :: Software Development :: Libraries :: Application Frameworks
Classifier: Topic :: Software Development :: Libraries :: Python Modules
Classifier: Topic :: Text Editors
Classifier: Topic :: Text Processing
Classifier: Topic :: Text Processing :: Markup
Classifier: Topic :: Text Processing :: Markup :: HTML
Provides-Extra: spellcheck
Requires-Dist: Django (>=3.2,<5.0)
Requires-Dist: pyenchant (>=3.1,<4.0) ; extra == "spellcheck"
Project-URL: Documentation, https://django-tinymce4-widget.readthedocs.io
Project-URL: Repository, https://github.com/browniebroke/django-tinymce4-widget
